stripstats/__init__.py
stripstats/function.py
stripstats/hyp_test.py
stripstats/io.py
stripstats-0.0.1.dist-info/METADATA
stripstats-0.0.1.dist-info/WHEEL
stripstats-0.0.1.dist-info/licenses/LICENSE
stripstats-0.0.1.dist-info/RECORD
